graphql_jwt/__init__.py
graphql_jwt/backends.py
graphql_jwt/compat.py
graphql_jwt/decorators.py
graphql_jwt/exceptions.py
graphql_jwt/middleware.py
graphql_jwt/mixins.py
graphql_jwt/mutations.py
graphql_jwt/path.py
graphql_jwt/relay.py
graphql_jwt/settings.py
graphql_jwt/shortcuts.py
graphql_jwt/signals.py
graphql_jwt/testcases.py
graphql_jwt/utils.py
graphql_jwt/locale/ar/LC_MESSAGES/django.mo
graphql_jwt/locale/ar/LC_MESSAGES/django.po
graphql_jwt/locale/es/LC_MESSAGES/django.mo
graphql_jwt/locale/es/LC_MESSAGES/django.po
graphql_jwt/locale/fr/LC_MESSAGES/django.mo
graphql_jwt/locale/fr/LC_MESSAGES/django.po
graphql_jwt/locale/nl/LC_MESSAGES/django.mo
graphql_jwt/locale/nl/LC_MESSAGES/django.po
graphql_jwt/locale/pt_BR/LC_MESSAGES/django.mo
graphql_jwt/locale/pt_BR/LC_MESSAGES/django.po
graphql_jwt/locale/zh_Hans/LC_MESSAGES/django.po
graphql_jwt/refresh_token/__init__.py
graphql_jwt/refresh_token/apps.py
graphql_jwt/refresh_token/decorators.py
graphql_jwt/refresh_token/managers.py
graphql_jwt/refresh_token/mixins.py
graphql_jwt/refresh_token/models.py
graphql_jwt/refresh_token/mutations.py
graphql_jwt/refresh_token/relay.py
graphql_jwt/refresh_token/shortcuts.py
graphql_jwt/refresh_token/signals.py
graphql_jwt/refresh_token/utils.py
graphql_jwt/refresh_token/admin/__init__.py
graphql_jwt/refresh_token/admin/filters.py
graphql_jwt/refresh_token/locale/ar/LC_MESSAGES/django.mo
graphql_jwt/refresh_token/locale/ar/LC_MESSAGES/django.po
graphql_jwt/refresh_token/locale/es/LC_MESSAGES/django.mo
graphql_jwt/refresh_token/locale/es/LC_MESSAGES/django.po
graphql_jwt/refresh_token/locale/fr/LC_MESSAGES/django.mo
graphql_jwt/refresh_token/locale/fr/LC_MESSAGES/django.po
graphql_jwt/refresh_token/locale/nl/LC_MESSAGES/django.mo
graphql_jwt/refresh_token/locale/nl/LC_MESSAGES/django.po
graphql_jwt/refresh_token/locale/pt_BR/LC_MESSAGES/django.mo
graphql_jwt/refresh_token/locale/pt_BR/LC_MESSAGES/django.po
graphql_jwt/refresh_token/locale/zh_Hans/LC_MESSAGES/django.po
django_graphql_jwt-0.3.3.dist-info/AUTHORS.rst
django_graphql_jwt-0.3.3.dist-info/LICENSE
django_graphql_jwt-0.3.3.dist-info/METADATA
django_graphql_jwt-0.3.3.dist-info/WHEEL
django_graphql_jwt-0.3.3.dist-info/top_level.txt
django_graphql_jwt-0.3.3.dist-info/RECORD
